{
    "nombre": "Básica",
    "img": "../../img/fija(serie40).png",
    "ceja": [
        { "nombre": "Sin ceja", "img": "../../img/sinCeja.png " },
        { "nombre": "Ceja", "img": "../../img/ceja.png" },
        { "nombre": "Ceja enfrente", "img": "../../img/ceja_frente.png" }
    ],
    "tipoVidrio": [
        {
            "nombre": "Vidrio sencillo",
            "img": "../../img/vidrioSencillo.png ",
            "tipos": [
              { 
                "nombre": "Claro", 
                "img": "../../img/vidrioSenci.png", 
                "precio": [ 
                  { "tipo": "fijoserie40", 
                    "tipos": [ { "fija": 23.98 }, { "doblefijaapilada": 24.04 } , { "triplefijapilada": 24.03 }, { "doblefija": 61.17 }, { "triplefija": 98.31  } ] 
                  },
                  {
                    "tipo": "corrediza",
                    "tipos": [ { "corrediza": 33.27 }, { "corredizaxox": 39.5 }, { "corredizaox-o": 33.27 }, { "corredizao-xo": 33.27 }, { "corredizao-xox": 39.5 } ]
                  },
                  {
                    "tipo": "guillotina",
                    "tipos": [ { "guillotina": 33.27 }, { "dobleguillotina": 39.95 }, { "oxo": 107.55 }, { "xox": 116.78 }, { "orio": 33.17 } ]
                  },
                  {
                    "tipo": "arcosyfiguras",
                    "tipos": []
                  }
                ] 
              },
              { "nombre": "Baño", "img": "../../img/vidrioSenciBano.png", 
                "precio": [ 
                  { "tipo": "fijoserie40", 
                    "tipos": [ { "fija" : 28.74 }, { "doblefijaapilada": 28.82 }, { "triplefijapilada": 28.81 }, { "doblefija": 70.71 }, { "triplefija": 112.64 } ] 
                  },
                  {
                    "tipo": "corrediza",
                    "tipos": [ { "corrediza": 37.56 }, { "corredizaxox": 43.54 }, { "corredizaox-o": 37.56 }, { "corredizao-xo": 37.56 }, { "corredizao-xox": 43.55 } ]
                  },
                  {
                    "tipo": "guillotina",
                    "tipos": [ { "guillotina": 37.56 }, { "dobleguillotina": 45.88 }, { "oxo": 121.4 }, { "xox": 130.15 }, { "orio": 37.45 } ]
                  },
                  {
                    "tipo": "arcosyfiguras",
                    "tipos": []
                  }
                ] 
              },
              { "nombre": "FiltraSol", "img": "../../img/vidrioSenci.png", 
                "precio": [
                  {
                    "tipo": "fijoserie40",
                    "tipos": [ { "fija": 33.34 }, { "doblefijaapilada": 33.42 }, { "triplefijapilada": 33.42 }, { "doblefija": 79.92 }, { "triplefija": 126.47 } ]
                  },
                  {
                    "tipo": "corrediza",
                    "tipos": [ { "corrediza": 45.60 }, { "corredizaxox": 53.82 }, { "corredizaox-o": 45.6 }, { "corredizao-xo": 45.6 }, { "corredizao-xox": 53.82 } ]
                  },
                  {
                    "tipo": "guillotina",
                    "tipos": [ { "guillotina": 45.6 }, { "dobleguillotina": 54.96 }, { "oxo": 138.64 }, { "xox": 150.8 }, { "orio": 45.46 } ]
                  },
                  {
                    "tipo": "arcosyfiguras",
                    "tipos": []
                  }
                ] 
              },
              { "nombre": "ReflecteSol", "img": "../../img/vidrioSenci.png", 
                "precio": [
                  {
                    "tipo": "fijoserie40",
                    "tipos": [ { "fija": 49.46 }, {"doblefijaapilada": 49.60 }, { "triplefijapilada": 49.56 }, { "doblefija": 112.22 }, { "triplefija": 174.91 } ]
                  },
                  {
                    "tipo": "corrediza",
                    "tipos": [ { "corrediza": 60.11 }, { "corredizaxox": 67.51 }, { "corredizaox-o": 60.11 }, { "corredizao-xo": 60.11 }, { "corredizao-xox": 67.52 } ]
                  },
                  {
                    "tipo": "guillotina",
                    "tipos": [ { "guillotina": 60.11 }, { "dobleguillotina": 75.07 }, { "oxo": 185.45 }, { "xox": 195.98 }, { "orio": 59.93 } ]
                  },
                  {
                    "tipo": "arcosyfiguras",
                    "tipos": []
                  }
                ] 
              }
            ]
        },
        {
            "nombre": "Vidrio doble",
            "img": "../../img/vidrio_dob.png",
            "tipos": [
                { 
                  "nombre": "Claro", 
                  "img": "../../img/vidrio_dob.png", 
                  "precio": [
                    {
                      "tipo": "fijoserie40",
                      "tipos": [ { "fija": 38.00 }, { "doblefijaapilada": 38.1 }, { "triplefijapilada": 38.09 }, { "doblefija": 89.26 }, { "triplefija": 140.47 } ]
                    },
                    {
                      "tipo": "corrediza",
                      "tipos": [ { "corrediza": 46.25 }, { "corredizaxox": 56.09 }, { "corredizaox-o": 46.25 }, { "corredizao-xo": 46.24 }, { "corredizao-xox": 56.09 } ]
                    },
                    {
                      "tipo": "guillotina",
                      "tipos": [ { "guillotina": 46.96 }, { "dobleguillotina": 55.87 }, { "oxo": 149.33 }, { "xox": 158.19 }, { "orio": 46.82 } ]
                    },
                    {
                      "tipo": "arcosyfiguras",
                      "tipos": []
                    }
                  ] 
                },
                { 
                  "nombre": "Low-E", 
                  "img": "../../img/vidrio_dob_lowe.png", 
                  "precio": [
                    {
                      "tipo": "fijoserie40",
                      "tipos": [ { "fija": 42.47 }, { "doblefijaapilada": 42.58 }, { "triplefijapilada": 42.58 }, { "doblefija": 98.21 }, { "triplefija": 153.92 } ]
                    },
                    {
                      "tipo": "corrediza",
                      "tipos": [ { "corrediza": 55.72 }, { "corredizaxox": 63.95 }, { "corredizaox-o": 55.72 }, { "corredizao-xo": 55.71 }, { "corredizao-xox": 63.95 } ]
                    },
                    {
                      "tipo": "guillotina",
                      "tipos": [ { "guillotina": 55.71 }, { "dobleguillotina": 67.87 }, { "oxo": 167.04 }, { "xox": 180.2 }, { "orio": 55.55 } ]
                    },
                    {
                      "tipo": "arcosyfiguras",
                      "tipos": []
                    }
                  ]
                },
                { 
                  "nombre": "Claro / Baño", 
                  "img": "../../img/vidrio_dob.png", 
                  "precio": [
                    {
                      "tipo": "fijoserie40",
                      "tipos": [ { "fija": 43.76 }, { "doblefijaapilada": 43.88 }, { "triplefijapilada": 43.85 }, { "doblefija": 100.79 }, { "triplefija": 157.75 } ]
                    },
                    {
                      "tipo": "corrediza",
                      "tipos": [ { "corrediza": 53.67 }, { "corredizaxox": 66.42 }, { "corredizaox-o": 53.67 }, { "corredizao-xo": 53.67 }, { "corredizao-xox": 66.42 } ]
                    },
                    {
                      "tipo": "guillotina",
                      "tipos": [ { "guillotina": 54.38 }, { "dobleguillotina": 66.05 }, { "oxo": 168.28 }, { "xox": 178.8 }, { "orio": 54.75 } ]
                    },
                    {
                      "tipo": "arcosyfiguras",
                      "tipos": []
                    }
                  ]  
                },
                { 
                  "nombre": "Low-E / Baño", 
                  "img": "../../img/vidrio_dob_lowe.png", 
                  "precio": [
                    {
                      "tipo": "fijoserie40",
                      "tipos": [ { "fija": 48.83 }, { "doblefijaapilada": 48.95 }, { "triplefijapilada": 48.95 }, { "doblefija": 110.96 } , { "triplefija": 173.03 } ]
                    },
                    {
                      "tipo": "corrediza",
                      "tipos": [ { "corrediza": 61.44 }, { "corredizaxox": 69.35 }, { "corredizaox-o": 61.44 }, { "corredizao-xo": 61.45 }, { "corredizao-xox": 69.35 } ]
                    },
                    {
                      "tipo": "guillotina",
                      "tipos": [ { "guillotina": 61.45 }, { "dobleguillotina": 75.79 }, { "oxo": 185.52 }, { "xox": 198.0 }, { "orio": 61.86 } ]
                    },
                    {
                      "tipo": "arcosyfiguras",
                      "tipos": []
                    }
                  ]
                },
                { 
                  "nombre": "Low-E / FiltraSol", 
                  "img": "../../img/vidrio_dob_lowe.png", 
                  "precio": [
                    {
                      "tipo": "fijoserie40",
                      "tipos": [ { "fija": 43.85 }, { "doblefijaapilada": 43.97 }, { "triplefijapilada": 43.95 }, { "doblefija": 100.97 }, { "triplefija": 158.04 } ]
                    },
                    {
                      "tipo": "corrediza",
                      "tipos": [ { "corrediza": 56.95 }, { "corredizaxox": 65.12 }, { "corredizaox-o": 56.96 }, { "corredizao-xo": 56.96 }, { "corredizao-xox": 65.11 } ]
                    },
                    {
                      "tipo": "guillotina",
                      "tipos": [ { "guillotina": 56.96 }, { "dobleguillotina": 69.58 }, { "oxo": 171.04 }, { "xox": 184.05 }, { "orio": 57.34 } ]
                    },
                    {
                      "tipo": "arcosyfiguras",
                      "tipos": []
                    }
                  ]
                },
                { 
                  "nombre": "Low-E / ReflecteSol", 
                  "img": "../../img/vidrio_dob_lowe.png", 
                  "precio": [
                    {
                      "tipo": "fijoserie40",
                      "tipos": [ { "fija": 59.89 }, { "doblefijaapilada": 60.07 }, { "triplefijapilada": 60.04 }, { "doblefija": 133.15 } , { "triplefija": 206.31 } ]
                    },
                    {
                      "tipo": "corrediza",
                      "tipos": [ { "corrediza": 71.39 }, { "corredizaxox": 78.72 }, { "corredizaox-o": 71.39 }, { "corredizao-xo": 60.45 }, { "corredizao-xox": 78.71 } ]
                    },
                    {
                      "tipo": "guillotina",
                      "tipos": [ { "guillotina": 71.39 }, { "dobleguillotina": 89.57 }, { "oxo": 217.66 }, { "xox": 229.0 }, { "orio": 71.88 } ]
                    },
                    {
                      "tipo": "arcosyfiguras",
                      "tipos": []
                    }
                  ]
                },
                { 
                  "nombre": "FiltraSol / Claro", 
                  "img": "../../img/vidrio_dob.png", 
                  "precio": [
                    {
                      "tipo": "fijoserie40",
                      "tipos": [ { "fija": 40.50 }, { "doblefijaapilada": 40.61 }, { "triplefijapilada": 40.60 }, { "doblefija": 94.26 }, { "triplefija": 147.99 } ]
                    },
                    {
                      "tipo": "corrediza",
                      "tipos": [ { "corrediza": 51.02 }, { "corredizaxox": 59.50 }, { "corredizaox-o": 51.01 }, { "corredizao-xo": 51.02 }, { "corredizao-xox": 59.5 } ]
                    },
                    {
                      "tipo": "guillotina",
                      "tipos": [ { "guillotina": 51.01 }, { "dobleguillotina": 61.37 }, { "oxo": 158.41 }, { "xox": 168.82 }, { "orio": 51.37 } ]
                    },
                    {
                      "tipo": "arcosyfiguras",
                      "tipos": []
                    }
                  ]
                },
                { 
                  "nombre": "FiltraSol / Baño", 
                  "img": "../../img/vidrio_dob.png", 
                  "precio": [
                    {
                      "tipo": "fijoserie40",
                      "tipos": [ { "fija": 46.86 }, { "doblefijaapilada": 47.0 }, { "triplefijapilada": 46.96 }, { "doblefija": 107.01 }, { "triplefija": 167.1 } ]
                    },
                    {
                      "tipo": "corrediza",
                      "tipos": [ { "corrediza": 59.66 }, { "corredizaxox": 67.66 }, { "corredizaox-o": 59.66 }, { "corredizao-xo": 59.67 }, { "corredizao-xox": 66.85 } ]
                    },
                    {
                      "tipo": "guillotina",
                      "tipos": [ { "guillotina": 59.67 }, { "dobleguillotina": 73.35 }, { "oxo": 179.8 }, { "xox": 192.47 }, { "orio": 60.07 } ]
                    },
                    {
                      "tipo": "arcosyfiguras",
                      "tipos": []
                    }
                  ]
                },
                { 
                  "nombre": "ReflecteSol / Claro", 
                  "img": "../../img/vidrio_dob.png", 
                  "precio": [
                    {
                      "tipo": "fijoserie40",
                      "tipos": [ { "fija": 189.65 }, { "doblefijaapilada": 56.71 }, { "triplefijapilada": 56.7 }, { "doblefija": 126.44 }, { "triplefija": 196.26 } ]
                    },
                    {
                      "tipo": "corrediza",
                      "tipos": [ { "corrediza": 68.38 }, { "corredizaxox": 75.87 }, { "corredizaox-o": 68.38 }, { "corredizao-xo": 69.38 }, { "corredizao-xox": 75.86 } ]
                    },
                    {
                      "tipo": "guillotina",
                      "tipos": [ { "guillotina": 68.38 }, { "dobleguillotina": 85.41 }, { "oxo": 207.94 }, { "xox": 219.62 }, { "orio": 68.85 } ]
                    },
                    {
                      "tipo": "arcosyfiguras",
                      "tipos": []
                    }
                  ]
                },
                { 
                  "nombre": "ReflecteSol / FiltraSol", 
                  "img": "../../img/vidrio_dob.png", 
                  "precio": [
                    {
                      "tipo": "fijoserie40",
                      "tipos": [ { "fija": 57.92 }, { "doblefijaapilada": 58.09 }, { "triplefijapilada": 58.06 }, { "doblefija": 129.18 }, { "triplefija": 200.38 } ]
                    },
                    {
                      "tipo": "corrediza",
                      "tipos": [ { "corrediza": 69.61 }, { "corredizaxox": 77.03 }, { "corredizaox-o": 69.61 }, { "corredizao-xo": 69.61 }, { "corredizao-xox": 77.03 } ]
                    },
                    {
                      "tipo": "guillotina",
                      "tipos": [ { "guillotina": 69.61 }, { "dobleguillotina": 87.13 }, { "oxo": 211.94 }, { "xox": 223.47 }, { "orio": 70.09 } ]
                    },
                    {
                      "tipo": "arcosyfiguras",
                      "tipos": []
                    }
                  ]
                },
                { 
                  "nombre": "ReflecteSol / Baño UF", 
                  "img": "../../img/vidrio_dob.png", 
                  "precio": [
                    {
                      "tipo": "fijoserie40",
                      "tipos": [ { "fija": 0 }, { "doblefijaapilada": 0 }, { "triplefijapilada": 0 }, { "doblefija": 0 }, { "triplefija": 0 } ]
                    },
                    {
                      "tipo": "corrediza",
                      "tipos": [ { "corrediza": 0.0 }, { "corredizaxox": 0.0 }, { "corredizaox-o": 0 }, { "corredizao-xo": 0 }, { "corredizao-xox": 0 } ]
                    },
                    {
                      "tipo": "guillotina",
                      "tipos": [ { "guillotina": 0 }, { "dobleguillotina": 0 }, { "oxo": 0 }, { "xox": 0 }, { "orio": 0 } ]
                    },
                    {
                      "tipo": "arcosyfiguras",
                      "tipos": []
                    }
                  ]
                }
            ]
        },
        {
            "nombre": "Vidrio doble con marginal",
            "img": "../../img/vidrio_dob_marginal.png",
            "tipos": [
                { 
                  "nombre": "Claro con marginal", 
                  "img": "../../img/vidrio_dob_marginal.png", 
                  "precio": [
                    {
                      "tipo": "fijoserie40",
                      "tipos": [ { "fija": 43.83 }, { "doblefijaapilada": 43.95 }, { "triplefijapilada": 43.93 }, { "doblefija": 100.93 }, { "triplefija": 158.0 } ]
                    },
                    {
                      "tipo": "corrediza",
                      "tipos": [ { "corrediza": 50.97 }, { "corredizaxox": 62.1 }, { "corredizaox-o": 50.46 }, { "corredizao-xo": 50.96 }, { "corredizao-xox": 62.09 } ]
                    },
                    {
                      "tipo": "guillotina",
                      "tipos": [ { "guillotina": 52.94 }, { "dobleguillotina": 62.78 }, { "oxo": 166.99 }, { "xox": 175.99 } ]
                    },
                    {
                      "tipo": "arcosyfiguras",
                      "tipos": []
                    }
                  ] 
                },
                { 
                  "nombre": "Low-E con marginal", 
                  "img": "../../img/vidrio_dob_lowe_marginal.png", 
                  "precio": [
                    {
                      "tipo": "fijoserie40",
                      "tipos": [ { "fija": 46.39 }, { "doblefijaapilada": 46.51 }, { "triplefijapilada": 46.5 }, { "doblefija": 106.08 }, { "triplefija": 165.7 } ]
                    },
                    {
                      "tipo": "corrediza",
                      "tipos": [ { "corrediza": 59.38 }, { "corredizaxox": 67.31 }, { "corredizaox-o": 58.8 }, { "corredizao-xo": 59.38 }, { "corredizao-xox": 67.31 } ]
                    },
                    {
                      "tipo": "guillotina",
                      "tipos": [ { "guillotina": 59.38 }, { "dobleguillotina": 72.71 }, { "oxo": 178.58 }, { "xox": 191.44 } ]
                    },
                    {
                      "tipo": "arcosyfiguras",
                      "tipos": []
                    }
                  ] 
                },
                { 
                  "nombre": "Claro / Baño con marginal", 
                  "img": "../../img/vidrio_dob_marginal.png", 
                  "precio": [
                    {
                      "tipo": "fijoserie40",
                      "tipos": [ { "fija": 49.74 }, { "doblefijaapilada": 49.87 }, { "triplefijapilada": 49.86 }, { "doblefija": 112.77 }, { "triplefija": 175.77 } ]
                    },
                    {
                      "tipo": "corrediza",
                      "tipos": [ { "corrediza": 58.6 }, { "corredizaxox": 72.43 }, { "corredizaox-o": 58.02 }, { "corredizao-xo": 58.59 }, { "corredizao-xox": 72.43 } ]
                    },
                    {
                      "tipo": "guillotina",
                      "tipos": [ { "guillotina": 65.36 }, { "dobleguillotina": 73.24 }, { "oxo": 191.27 }, { "xox": 206.77 } ]
                    },
                    {
                      "tipo": "arcosyfiguras",
                      "tipos": []
                    }
                  ]
                },
                { 
                  "nombre": "Low-E / Baño con marginal", 
                  "img": "../../img/vidrio_dob_lowe_marginal.png", 
                  "precio": [
                    {
                      "tipo": "fijoserie40",
                      "tipos": [ { "fija": 52.91 }, { "doblefijaapilada": 53.04 }, { "triplefijapilada": 53.03 }, { "doblefija": 119.12 }, { "triplefija": 185.29 } ]
                    },
                    {
                      "tipo": "corrediza",
                      "tipos": [ { "corrediza": 65.25 }, { "corredizaxox": 72.85 }, { "corredizaox-o": 64.61 }, { "corredizao-xo": 65.25 }, { "corredizao-xox": 72.85 } ]
                    },
                    {
                      "tipo": "guillotina",
                      "tipos": [ { "guillotina": 65.25 }, { "dobleguillotina": 80.84 }, { "oxo": 197.5 }, { "xox": 209.7 } ]
                    },
                    {
                      "tipo": "arcosyfiguras",
                      "tipos": []
                    }
                  ]
                },
                { 
                  "nombre": "Low-E / FiltraSol con marginal", 
                  "img": "../../img/vidrio_dob_lowe_marginal.png", 
                  "precio": [
                    {
                      "tipo": "fijoserie40",
                      "tipos": [ { "fija": 47.80 }, { "doblefijaapilada": 47.91 }, { "triplefijapilada": 47.92 }, { "doblefija": 108.89 }, { "triplefija": 169.94 } ]
                    },
                    {
                      "tipo": "corrediza",
                      "tipos": [ { "corrediza": 60.64 }, { "corredizaxox": 68.5 }, { "corredizaox-o": 60.06 }, { "corredizao-xo": 60.65 }, { "corredizao-xox": 68.5 } ]
                    },
                    {
                      "tipo": "guillotina",
                      "tipos": [ { "guillotina": 60.65 }, { "dobleguillotina": 74.48 }, { "oxo": 182.67 }, { "xox": 195.39 } ]
                    },
                    {
                      "tipo": "arcosyfiguras",
                      "tipos": []
                    }
                  ]
                },
                { 
                  "nombre": "Low-E / ReflecteSol con marginal", 
                  "img": "../../img/vidrio_dob_lowe_marginal.png", 
                  "precio": [
                    {
                      "tipo": "fijoserie40",
                      "tipos": [ { "fija": 64.26 }, { "doblefijaapilada": 64.42 }, { "triplefijapilada": 64.41 }, { "doblefija": 141.85 }, { "triplefija": 219.41 } ]
                    },
                    {
                      "tipo": "corrediza",
                      "tipos": [ { "corrediza": 75.45 }, { "corredizaxox": 82.44 }, { "corredizaox-o": 74.71 }, { "corredizao-xo": 75.45 }, { "corredizao-xox": 82.44 } ]
                    },
                    {
                      "tipo": "guillotina",
                      "tipos": [ { "guillotina": 75.45 }, { "dobleguillotina": 94.97 }, { "oxo": 230.45 }, { "xox": 241.48 } ]
                    },
                    {
                      "tipo": "arcosyfiguras",
                      "tipos": []
                    }
                  ]
                },
                { 
                  "nombre": "FiltraSol / Claro con marginal", 
                  "img": "../../img/vidrio_dob_marginal.png", 
                  "precio": [
                    {
                      "tipo": "fijoserie40",
                      "tipos": [ { "fija": 44.37 }, { "doblefijaapilada": 44.50 }, { "triplefijapilada": 44.48 }, { "doblefija": 102.03 }, { "triplefija": 159.64 } ]
                    },
                    {
                      "tipo": "corrediza",
                      "tipos": [ { "corrediza": 54.56 }, { "corredizaxox": 62.76 }, { "corredizaox-o": 54.03 }, { "corredizao-xo": 54.56 }, { "corredizao-xox": 62.75 } ]
                    },
                    {
                      "tipo": "guillotina",
                      "tipos": [ { "guillotina": 54.57 }, { "dobleguillotina": 66.06 }, { "oxo": 169.71 }, { "xox": 179.79 } ]
                    },
                    {
                      "tipo": "arcosyfiguras",
                      "tipos": []
                    }
                  ] 
                },
                { 
                  "nombre": "FiltraSol / Baño con marginal", 
                  "img": "../../img/vidrio_dob_marginal.png", 
                  "precio": [
                    {
                      "tipo": "fijoserie40",
                      "tipos": [ { "fija": 50.89 }, { "doblefijaapilada": 51.03 }, { "triplefijapilada": 51.01 }, { "doblefija": 115.07 }, { "triplefija": 179.22 } ]
                    },
                    {
                      "tipo": "corrediza",
                      "tipos": [ { "corrediza": 63.43 }, { "corredizaxox": 71.12 }, { "corredizaox-o": 62.81 }, { "corredizao-xo": 63.43 }, { "corredizao-xox": 71.12 } ]
                    },
                    {
                      "tipo": "guillotina",
                      "tipos": [ { "guillotina": 63.43 }, { "dobleguillotina": 78.34 }, { "oxo": 191.63 }, { "xox": 204.05 } ]
                    },
                    {
                      "tipo": "arcosyfiguras",
                      "tipos": []
                    }
                  ] 
                },
                { 
                  "nombre": "ReflecteSol / Claro con marginal", 
                  "img": "../../img/vidrio_dob_marginal.png", 
                  "precio": [
                    {
                      "tipo": "fijoserie40",
                      "tipos": [ { "fija": 60.83 }, { "doblefijaapilada": 61.0 }, { "triplefijapilada": 61.24 }, { "doblefija": 135.0 }, { "triplefija": 209.1 } ]
                    },
                    {
                      "tipo": "corrediza",
                      "tipos": [ { "corrediza": 72.46 }, { "corredizaxox": 79.52 }, { "corredizaox-o": 71.66 }, { "corredizao-xo": 72.36 }, { "corredizao-xox": 79.52 } ]
                    },
                    {
                      "tipo": "guillotina",
                      "tipos": [ { "guillotina": 72.36 }, { "dobleguillotina": 90.71 }, { "oxo": 220.49 }, { "xox": 231.88 } ]
                    },
                    {
                      "tipo": "arcosyfiguras",
                      "tipos": []
                    }
                  ]
                },
                { 
                  "nombre": "ReflecteSol / FiltraSol con marginal", 
                  "img": "../../img/vidrio_dob_marginal.png", 
                  "precio": [
                    {
                      "tipo": "fijoserie40",
                      "tipos": [ { "fija": 62.24 }, { "doblefijaapilada": 62.41 }, { "triplefijapilada": 62.38 }, { "doblefija": 137.83 }, { "triplefija": 213.33 } ]
                    },
                    {
                      "tipo": "corrediza",
                      "tipos": [ { "corrediza": 73.62 }, { "corredizaxox": 80.72 }, { "corredizaox-o": 72.91 }, { "corredizao-xo": 73.63 }, { "corredizao-xox": 80.72 } ]
                    },
                    {
                      "tipo": "guillotina",
                      "tipos": [ { "guillotina": 73.63 }, { "dobleguillotina": 92.47 }, { "oxo": 224.57 }, { "xox": 235.8 } ]
                    },
                    {
                      "tipo": "arcosyfiguras",
                      "tipos": []
                    }
                  ] 
                },
                { 
                  "nombre": "ReflecteSol / Baño UF con marginal", 
                  "img": "../../img/vidrio_dob_marginal.png", 
                  "precio": [
                    {
                      "tipo": "fijoserie40",
                      "tipos": [ { "fija": 0 }, { "doblefijaapilada": 0 }, { "triplefijapilada": 0 }, { "doblefija": 0 }, { "triplefija": 0 } ]
                    },
                    {
                      "tipo": "corrediza",
                      "tipos": [ { "corrediza": 0 }, { "corredizaxox": 0 }, { "corredizaox-o": 0 }, { "corredizao-xo": 0 }, { "corredizao-xox": 0 } ]
                    },
                    {
                      "tipo": "guillotina",
                      "tipos": [ { "guillotina": 0 }, { "dobleguillotina": 0 }, { "oxo": 0 }, { "xox": 0 } ]
                    },
                    {
                      "tipo": "arcosyfiguras",
                      "tipos": []
                    }
                  ]
                }
            ]
        },
        {
            "nombre": "Vidrio doble con cuadrícula",
            "img": "../../img/vidrio_dob_cuadricula.png",
            "tipos": [
              { 
                "nombre": "Claro con cuadrícula", 
                "img": "../../img/vidrio_dob_cuadricula.png", 
                "precio": [
                  {
                    "tipo": "fijoserie40",
                    "tipos": [ { "fija": 43.83 }, { "doblefijaapilada": 43.95 }, { "triplefijapilada": 43.93 }, { "doblefija": 100.93 }, { "triplefija": 158.0 } ]
                  },
                  {
                    "tipo": "corrediza",
                    "tipos": [ { "corrediza": 50.97 }, { "corredizaxox": 62.1 }, { "corredizaox-o": 50.46 }, { "corredizao-xo": 50.96 }, { "corredizao-xox": 62.09 } ]
                  },
                  {
                    "tipo": "guillotina",
                    "tipos": [ { "guillotina": 52.94 }, { "dobleguillotina": 62.78 }, { "oxo": 166.99 }, { "xox": 175.99 } ]
                  },
                  {
                    "tipo": "arcosyfiguras",
                    "tipos": []
                  }
                ] 
              },
              { 
                "nombre": "Low-E con cuadrícula", 
                "img": "../../img/vidrio_dob_lowe_cuadricula.png", 
                "precio": [
                  {
                    "tipo": "fijoserie40",
                    "tipos": [ { "fija": 46.39 }, { "doblefijaapilada": 46.51 }, { "triplefijapilada": 46.5 }, { "doblefija": 106.08 }, { "triplefija": 165.7 } ]
                  },
                  {
                    "tipo": "corrediza",
                    "tipos": [ { "corrediza": 59.38 }, { "corredizaxox": 67.31 }, { "corredizaox-o": 58.8 }, { "corredizao-xo": 59.38 }, { "corredizao-xox": 67.31 } ]
                  },
                  {
                    "tipo": "guillotina",
                    "tipos": [ { "guillotina": 59.38 }, { "dobleguillotina": 72.71 }, { "oxo": 178.58 }, { "xox": 191.44 } ]
                  },
                  {
                    "tipo": "arcosyfiguras",
                    "tipos": []
                  }
                ] 
              },
              { 
                "nombre": "Claro / Baño con cuadrícula", 
                "img": "../../img/vidrio_dob_cuadricula.png", 
                "precio": [
                  {
                    "tipo": "fijoserie40",
                    "tipos": [ { "fija": 49.74 }, { "doblefijaapilada": 49.87 }, { "triplefijapilada": 49.86 }, { "doblefija": 112.77 }, { "triplefija": 175.77 } ] 
                  },
                  {
                    "tipo": "corrediza",
                    "tipos": [ { "corrediza": 58.6 }, { "corredizaxox": 72.43 }, { "corredizaox-o": 58.02 }, { "corredizao-xo": 58.59 }, { "corredizao-xox": 72.43 } ]
                  },
                  {
                    "tipo": "guillotina",
                    "tipos": [ { "guillotina": 65.36 }, { "dobleguillotina": 73.24 }, { "oxo": 191.27 }, { "xox": 206.77 } ]
                  },
                  {
                    "tipo": "arcosyfiguras",
                    "tipos": []
                  }
                ]
              },
              { 
                "nombre": "Low-E / Baño con cuadrícula", 
                "img": "../../img/vidrio_dob_bano_lowe_cuadricula.png", 
                "precio": [
                  {
                    "tipo": "fijoserie40",
                    "tipos": [ { "fija": 52.91 }, { "doblefijaapilada": 53.04 }, { "triplefijapilada": 53.03 }, { "doblefija": 119.12 }, { "triplefija": 185.29 } ]
                  },
                  {
                    "tipo": "corrediza",
                    "tipos": [ { "corrediza": 65.25 }, { "corredizaxox": 72.85 }, { "corredizaox-o": 64.61 }, { "corredizao-xo": 65.25 }, { "corredizao-xox": 72.85 } ]
                  },
                  {
                    "tipo": "guillotina",
                    "tipos": [ { "guillotina": 65.25 }, { "dobleguillotina": 80.84 }, { "oxo": 197.5 }, { "xox": 209.7 } ]
                  },
                  {
                    "tipo": "arcosyfiguras",
                    "tipos": []
                  }
                ] 
              },
              {	
                "nombre": "Low-E / FiltraSol con cuadrícula", 
                "img": "../../img/vidrio_dob_lowe_cuadricula.png", 
                "precio": [
                  {
                    "tipo": "fijoserie40",
                    "tipos": [ { "fija": 47.8 }, { "doblefijaapilada": 47.91 }, { "triplefijapilada": 47.92 }, { "doblefija": 108.89 }, { "triplefija": 169.94 } ]
                  },
                  {
                    "tipo": "corrediza",
                    "tipos": [ { "corrediza": 60.64 }, { "corredizaxox": 68.5 }, { "corredizaox-o": 60.06 }, { "corredizao-xo": 60.65 }, { "corredizao-xox": 68.5 } ]
                  },
                  {
                    "tipo": "guillotina",
                    "tipos": [ { "guillotina": 60.65 }, { "dobleguillotina": 74.48 }, { "oxo": 182.67 }, { "xox": 195.39 } ]
                  },
                  {
                    "tipo": "arcosyfiguras",
                    "tipos": []
                  }
                ]	
              },
              {	
                "nombre": "Low-E / ReflecteSol con cuadrícula",	
                "img": "../../img/vidrio_dob_lowe_cuadricula.png", 
                "precio": [
                  {
                    "tipo": "fijoserie40",
                    "tipos": [ { "fija": 64.26 }, { "doblefijaapilada": 53.23 }, { "triplefijapilada": 64.41 }, { "doblefija": 141.85 }, { "triplefija": 219.41 } ]
                  },
                  {
                    "tipo": "corrediza",
                    "tipos": [ { "corrediza": 75.45 }, { "corredizaxox": 82.44 }, { "corredizaox-o": 74.71 }, { "corredizao-xo": 75.45 }, { "corredizao-xox": 82.44 } ]
                  },
                  {
                    "tipo": "guillotina",
                    "tipos": [ { "guillotina": 75.45 }, { "dobleguillotina": 94.97 }, { "oxo": 230.45 }, { "xox": 241.48 } ]
                  },
                  {
                    "tipo": "arcosyfiguras",
                    "tipos": []
                  }
                ] 
              },
              { 
                "nombre": "FiltraSol / Claro con cuadrícula", 
                "img": "../../img/vidrio_dob_cuadricula.png", 
                "precio": [
                  {
                    "tipo": "fijoserie40",
                    "tipos": [ { "fija": 44.37 }, { "doblefijaapilada": 44.5 }, { "triplefijapilada": 53.03 }, { "doblefija": 102.03 }, { "triplefija": 159.64 } ] 
                  },
                  {
                    "tipo": "corrediza",
                    "tipos": [ { "corrediza": 54.56 }, { "corredizaxox": 62.76 }, { "corredizaox-o": 54.03 }, { "corredizao-xo": 54.56 }, { "corredizao-xox": 62.75 } ]
                  },
                  {
                    "tipo": "guillotina",
                    "tipos": [ { "guillotina": 54.57 }, { "dobleguillotina": 66.06 }, { "oxo": 169.71 }, { "xox": 179.79 } ]
                  },
                  {
                    "tipo": "arcosyfiguras",
                    "tipos": []
                  }
                ]
              },
              { 
                "nombre": "FiltraSol / Baño con cuadrícula", 
                "img": "../../img/vidrio_dob_cuadricula.png", 
                "precio": [
                  {
                    "tipo": "fijoserie40",
                    "tipos": [ { "fija": 50.89 }, { "doblefijaapilada": 51.03 }, { "triplefijapilada": 51.01 }, { "doblefija": 115.07 }, { "triplefija": 179.22 } ]
                  },
                  {
                    "tipo": "corrediza",
                    "tipos": [ { "corrediza": 63.43 }, { "corredizaxox": 71.12 }, { "corredizaox-o": 62.84 }, { "corredizao-xo": 63.43 }, { "corredizao-xox": 71.12 } ]
                  },
                  {
                    "tipo": "guillotina",
                    "tipos": [ { "guillotina": 63.43 }, { "dobleguillotina": 78.34 }, { "oxo": 191.63 }, { "xox": 204.05 } ]
                  },
                  {
                    "tipo": "arcosyfiguras",
                    "tipos": []
                  }
                ] 
              },
              {	
                "nombre": "ReflecteSol / Claro con cuadrícula",	
                "img": "../../img/vidrio_dob_cuadricula.png", 
                "precio": [
                  {
                    "tipo": "fijoserie40",
                    "tipos": [ { "fija": 60.83 }, { "doblefijaapilada": 61.0 }, { "triplefijapilada": 60.97 }, { "doblefija": 135.0 }, { "triplefija": 209.1 } ]	
                  },
                  {
                    "tipo": "corrediza",
                    "tipos": [ { "corrediza": 72.36 }, { "corredizaxox": 79.52 }, { "corredizaox-o": 71.66 }, { "corredizao-xo": 72.36 }, { "corredizao-xox": 79.52 } ]
                  },
                  {
                    "tipo": "guillotina",
                    "tipos": [ { "guillotina": 72.36 }, { "dobleguillotina": 90.71 }, { "oxo": 220.49 }, { "xox": 231.88 } ]
                  },
                  {
                    "tipo": "arcosyfiguras",
                    "tipos": []
                  }
                ]
              },
              {	
                "nombre": "ReflecteSol / FiltraSol con cuadrícula",	
                "img": "../../img/vidrio_dob_cuadricula.png", 
                "precio": [
                  {
                    "tipo": "fijoserie40",
                    "tipos": [ { "fija": 62.24 }, { "doblefijaapilada": 62.41 }, { "triplefijapilada": 62.38 }, { "doblefija": 137.83 }, { "triplefija": 213.33 } ]
                  },
                  {
                    "tipo": "corrediza",
                    "tipos": [ { "corrediza": 73.62 }, { "corredizaxox": 80.72 }, { "corredizaox-o": 72.91 }, { "corredizao-xo": 73.63 }, { "corredizao-xox": 80.72 } ]
                  },
                  {
                    "tipo": "guillotina",
                    "tipos": [ { "guillotina": 73.63 }, { "dobleguillotina": 92.47 }, { "oxo": 224.57 }, { "xox": 235.8 } ]
                  },
                  {
                    "tipo": "arcosyfiguras",
                    "tipos": []
                  }
                ]	
              },
              {	
                "nombre": "ReflecteSol / Baño UF con cuadrícula",	
                "img": "../../img/vidrio_dob_cuadricula.png", 
                "precio": [
                  {
                    "tipo": "fijoserie40",
                    "tipos": [ { "fija": 0 }, { "doblefijaapilada": 0 }, { "triplefijapilada": 0 }, { "doblefija": 0 }, { "triplefija": 0 } ]
                  },
                  {
                    "tipo": "corrediza",
                    "tipos": [ { "corrediza": 0 }, { "corredizaxox": 0 }, { "corredizaox-o": 0 }, { "corredizao-xo": 0 }, { "corredizao-xox": 0 } ]
                  },
                  {
                    "tipo": "guillotina",
                    "tipos": [ { "guillotina": 0 }, { "dobleguillotina": 0 }, { "oxo": 0 }, { "xox": 0 } ]
                  },
                  {
                    "tipo": "arcosyfiguras",
                    "tipos": []
                  }
                ]	
              }
            ]
        }	
    ],
    "tipo": [
        {
            "nombre": "Fijo Serie 40",
            "img": "../../img/fija(serie40).png",
            "subtipo": [
                {
                    "nombre": "Fija",
                    "img": "../../img/fija(serie40).png",
                    "dimensiones": [
                        { "nombre": "Máximo", "ancho": "60", "alto": "72" },
                        { "nombre": "Mínimo", "ancho": "11.5", "alto": "11.5" }
                    ]
                },
                {
                    "nombre": "Doble fija apilada",
                    "img": "../../img/DobleFijoApilado(serie40).png",
                    "dimensiones": [
                        { "nombre": "Máximo", "ancho": "80", "alto": "20" },
                        { "nombre": "Mínimo", "ancho": "11", "alto": "11" }
                    ]
                },
                {
                    "nombre": "Triple fija apilada",
                    "img": "../../img/TripleFijaApilada(Serie40).png",
                    "dimensiones": [
                        { "nombre": "Máximo", "ancho": "80", "alto": "20" },
                        { "nombre": "Mínimo", "ancho": "11", "alto": "11" }
                    ]
                },
                {
                    "nombre": "Doble fija",
                    "img": "../../img/DobleFija(serie40).png",
                    "dimensiones": [
                        { "nombre": "Máximo", "ancho": "80", "alto": "20" },
                        { "nombre": "Mínimo", "ancho": "11", "alto": "11" }
                    ]
                },
                {
                    "nombre": "Triple fija",
                    "img": "../../img/TripleFijaApilada(Serie40).png",
                    "dimensiones": [
                        { "nombre": "Máximo", "ancho": "80", "alto": "20" },
                        { "nombre": "Mínimo", "ancho": "11", "alto": "11" }
                    ]
                }
            ]
        },
        {
            "nombre": "Corrediza",
            "img": "../../img/Corrediza.png",
            "subtipo": [
                {
                    "nombre": "Corrediza",
                    "img": "../../img/Corrediza.png",
                    "dimensiones": [
                        { "nombre": "Máximo", "ancho": "80", "alto": "20" },
                        { "nombre": "Mínimo", "ancho": "11", "alto": "11" }
                    ]
                },
                {
                    "nombre": "Corrediza XOX",
                    "img": "../../img/CorredizaXOX(serie40).png",
                    "dimensiones": [
                        { "nombre": "Máximo", "ancho": "80", "alto": "20" },
                        { "nombre": "Mínimo", "ancho": "11", "alto": "11" }
                    ]
                },
                {
                    "nombre": "Corrediza OX-O",
                    "img": "../../img/CorredizaOX-O.png",
                    "dimensiones": [
                        { "nombre": "Máximo", "ancho": "80", "alto": "20" },
                        { "nombre": "Mínimo", "ancho": "11", "alto": "11" }
                    ]
                },
                {
                    "nombre": "Corrediza O-XO",
                    "img": "../../img/CorredizaO-XO.png",
                    "dimensiones": [
                        { "nombre": "Máximo", "ancho": "80", "alto": "20" },
                        { "nombre": "Mínimo", "ancho": "11", "alto": "11" }
                    ]
                },
                {
                    "nombre": "Corrediza O-XOX",
                    "img": "../../img/CorredizaO-XOX.png",
                    "dimensiones": [
                        { "nombre": "Máximo", "ancho": "80", "alto": "20" },
                        { "nombre": "Mínimo", "ancho": "11", "alto": "11" }
                    ]
                }
            ]
        },
        {
            "nombre": "Guillotina",
            "img": "../../img/Guillotina.png",
            "subtipo": [
                {
                    "nombre": "Guillotina",
                    "img": "../../img/Guillotina.png",
                    "dimensiones": [
                        { "nombre": "Máximo", "ancho": "80", "alto": "20" },
                        { "nombre": "Mínimo", "ancho": "11", "alto": "11" }
                    ]
                },
                {
                    "nombre": "Doble guillotina",
                    "img": "../../img/DobleGuillotina.png",
                    "dimensiones": [
                        { "nombre": "Máximo", "ancho": "80", "alto": "20" },
                        { "nombre": "Mínimo", "ancho": "11", "alto": "11" }
                    ]
                },
                {
                    "nombre": "OXO",
                    "img": "../../img/GuillotinaOXO.png",
                    "dimensiones": [
                        { "nombre": "Máximo", "ancho": "80", "alto": "20" },
                        { "nombre": "Mínimo", "ancho": "11", "alto": "11" }
                    ]
                },
                {
                    "nombre": "XOX",
                    "img": "../../img/GuillotinaXOX.png",
                    "dimensiones": [
                        { "nombre": "Máximo", "ancho": "80", "alto": "20" },
                        { "nombre": "Mínimo", "ancho": "11", "alto": "11" }
                    ]
                },
                {
                    "nombre": "Orio",
                    "img": "../../img/GuillotinaOrio.png",
                    "dimensiones": [
                        { "nombre": "Máximo", "ancho": "80", "alto": "20" },
                        { "nombre": "Mínimo", "ancho": "11", "alto": "11" }
                    ]
                },
                {
                    "nombre": "Doble orio",
                    "img": "../../img/DobleGuillotinaOrio.png",
                    "dimensiones": [
                        { "nombre": "Máximo", "ancho": "80", "alto": "20" },
                        { "nombre": "Mínimo", "ancho": "11", "alto": "11" }
                    ]
                },
                {
                    "nombre": "O-OX",
                    "img": "../../img/GuillotinaO-OX.png",
                    "dimensiones": [
                        { "nombre": "Máximo", "ancho": "80", "alto": "20" },
                        { "nombre": "Mínimo", "ancho": "11", "alto": "11" }
                    ]
                },
                {
                    "nombre": "Con arco continuo",
                    "img": "../../img/GuillotinaConArcoContinuo.png",
                    "dimensiones": [
                        { "nombre": "Máximo", "ancho": "80", "alto": "20" },
                        { "nombre": "Mínimo", "ancho": "11", "alto": "11" }
                    ]
                }
            ]
        },
        {
            "nombre": "Arcos y figuras",
            "img": "../../img/ArcosyFiguras.png",
            "subtipo": [
                {
                    "nombre": "Triángulo isosceles",
                    "img": "../../img/TrianguloIsosceles.png",
                    "dimensiones": [
                        { "nombre": "Máximo", "ancho": "80", "alto": "20" },
                        { "nombre": "Mínimo", "ancho": "11", "alto": "11" }
                    ]
                },
                {
                    "nombre": "Forma AO",
                    "img": "../../img/ArcoAO.png",
                    "dimensiones": [
                        { "nombre": "Máximo", "ancho": "80", "alto": "20" },
                        { "nombre": "Mínimo", "ancho": "11", "alto": "11" }
                    ]
                },
                {
                    "nombre": "Hexagonal",
                    "img": "../../img/Hexagonal.png",
                    "dimensiones": [
                        { "nombre": "Máximo", "ancho": "80", "alto": "20" },
                        { "nombre": "Mínimo", "ancho": "11", "alto": "11" }
                    ]
                },
                {
                    "nombre": "Octagonal",
                    "img": "../../img/Octagonal.png",
                    "dimensiones": [
                        { "nombre": "Máximo", "ancho": "80", "alto": "20" },
                        { "nombre": "Mínimo", "ancho": "11", "alto": "11" }
                    ]
                },
                {
                    "nombre": "Triángulo rectángulo",
                    "img": "../../img/TrianguloRectangulo.png",
                    "dimensiones": [
                        { "nombre": "Máximo", "ancho": "80", "alto": "20" },
                        { "nombre": "Mínimo", "ancho": "11", "alto": "11" }
                    ]
                },
                {
                    "nombre": "Forma AO-O",
                    "img": "../../img/FormaAO-O.png",
                    "dimensiones": [
                        { "nombre": "Máximo", "ancho": "80", "alto": "20" },
                        { "nombre": "Mínimo", "ancho": "11", "alto": "11" }
                    ]
                },
                {
                    "nombre": "Figura AO",
                    "img": "../../img/FiguraAO.png",
                    "dimensiones": [
                        { "nombre": "Máximo", "ancho": "80", "alto": "20" },
                        { "nombre": "Mínimo", "ancho": "11", "alto": "11" }
                    ]
                },
                {
                    "nombre": "Figura AO-O",
                    "img": "../../img/FiguraAO-O.png",
                    "dimensiones": [
                        { "nombre": "Máximo", "ancho": "80", "alto": "20" },
                        { "nombre": "Mínimo", "ancho": "11", "alto": "11" }
                    ]
                },
                {
                    "nombre": "Circular",
                    "img": "../../img/Circular.png",
                    "dimensiones": [
                        { "nombre": "Máximo", "ancho": "80", "alto": "20" },
                        { "nombre": "Mínimo", "ancho": "11", "alto": "11" }
                    ]
                },
                {
                    "nombre": "Arco",
                    "img": "../../img/Arco.png",
                    "dimensiones": [
                        { "nombre": "Máximo", "ancho": "80", "alto": "20" },
                        { "nombre": "Mínimo", "ancho": "11", "alto": "11" }
                    ]
                },
                {
                    "nombre": "Arco media luna fijo",
                    "img": "../../img/ArcoMediaLunaFijo.png",
                    "dimensiones": [
                        { "nombre": "Máximo", "ancho": "80", "alto": "20" },
                        { "nombre": "Mínimo", "ancho": "11", "alto": "11" }
                    ]
                },
                {
                    "nombre": "Media luna con un fijo",
                    "img": "../../img/MediaLunacon1Fijo.png",
                    "dimensiones": [
                        { "nombre": "Máximo", "ancho": "80", "alto": "20" },
                        { "nombre": "Mínimo", "ancho": "11", "alto": "11" }
                    ]
                },
                {
                    "nombre": "Arco A-O-O",
                    "img": "../../img/ArcoA-O-O.png",
                    "dimensiones": [
                        { "nombre": "Máximo", "ancho": "80", "alto": "20" },
                        { "nombre": "Mínimo", "ancho": "11", "alto": "11" }
                    ]
                },
                {
                    "nombre": "Arco media luna 3 fijos",
                    "img": "../../img/ArcoMediaLunacon3Fijos.png",
                    "dimensiones": [
                        { "nombre": "Máximo", "ancho": "80", "alto": "20" },
                        { "nombre": "Mínimo", "ancho": "11", "alto": "11" }
                    ]
                },
                {
                    "nombre": "Arco AO",
                    "img": "../../img/ArcoAO.png",
                    "dimensiones": [
                        { "nombre": "Máximo", "ancho": "80", "alto": "20" },
                        { "nombre": "Mínimo", "ancho": "11", "alto": "11" }
                    ]
                },
                {
                    "nombre": "Fijo con arco",
                    "img": "../../img/FijoConArco.png",
                    "dimensiones": [
                        { "nombre": "Máximo", "ancho": "80", "alto": "20" },
                        { "nombre": "Mínimo", "ancho": "11", "alto": "11" }
                    ]
                },
                {
                    "nombre": "Arco media luna con 2 fijos",
                    "img": "../../img/ArcoMediaLunacon2Fijos.png",
                    "dimensiones": [
                        { "nombre": "Máximo", "ancho": "80", "alto": "20" },
                        { "nombre": "Mínimo", "ancho": "11", "alto": "11" }
                    ]
                },
                {
                    "nombre": "Arco AOOO luna con 3 fijos",
                    "img": "../../img/ArcoAOOOcon3Fijos.png",
                    "dimensiones": [
                        { "nombre": "Máximo", "ancho": "80", "alto": "20" },
                        { "nombre": "Mínimo", "ancho": "11", "alto": "11" }
                    ]
                },
                {
                    "nombre": "Catedral",
                    "img": "../../img/Catedral.png",
                    "dimensiones": [
                        { "nombre": "Máximo", "ancho": "80", "alto": "20" },
                        { "nombre": "Mínimo", "ancho": "11", "alto": "11" }
                    ]
                }
            ]
        }
    ],
    "colores": [
      {
        "nombre": "Blanco",
        "img": "../../img/Blanco.png",
        "color": [ 
          {"nombre": "Bronze","precioExterior": 1872.50,"precioInterior":3744.99},
          {"nombre": "Negro","precioExterior": 1872.50,"precioInterior":3744.99},
          {"nombre": "Cranberry","precioExterior": 1872.50,"precioInterior":3744.99},
          {"nombre": "Charcoal Gray","precioExterior": 1872.50,"precioInterior":3744.99},
          {"nombre": "Azul","precioExterior": 1872.50,"precioInterior":3744.99},
          {"nombre": "Rojo Caliente","precioExterior": 1872.50,"precioInterior":3744.99},
          {"nombre": "Metallic Silver","precioExterior": 3744.99,"precioInterior":7489.99},
          {"nombre": "Wicker","precioExterior": 1872.50,"precioInterior":3744.99}
        ]
      },
      {
        "nombre": "Clay",
        "img": "../../img/Clay.png",
        "color": [ 
          {"nombre": "Bronze","precioExterior": 1872.50,"precioInterior":3744.99},
          {"nombre": "Negro","precioExterior": 1872.50,"precioInterior":3744.99},
          {"nombre": "Cranberry","precioExterior": 1872.50,"precioInterior":3744.99},
          {"nombre": "Charcoal Gray","precioExterior": 1872.50,"precioInterior":3744.99},
          {"nombre": "Azul","precioExterior": 1872.50,"precioInterior":3744.99},
          {"nombre": "Rojo Caliente","precioExterior": 1872.50,"precioInterior":3744.99},
          {"nombre": "Metallic Silver","precioExterior": 3744.99,"precioInterior":7489.99},
          {"nombre": "Wicker","precioExterior": 1872.50,"precioInterior":3744.99}
        ]
      }
	  ]
}